{
  "objectInfo" : {
    "id" : "2fUhkzQWsAij93VdEiReO8",
    "name" : "Parse_Versioning_BuiltIn",
    "type" : "PARSE",
    "metadata" : {
      "modelVersion" : {
        "major" : 1,
        "minor" : 0
      },
      "repoInfo" : {
        "repoHandle" : "2fUhkzQWsAij93VdEiReO8"
      },
      "contextAttributes" : [ ],
      "additionalInfo" : {
        "description" : "Parse_Versioning_BuiltIn",
        "contentType" : "Binary",
        "documentState" : "VALID"
      }
    }
  },
  "dataFileExtension" : "json",
  "updateTime" : "2025-02-11T06:31:43.097Z",
  "objectRefs" : [ ],
  "readableFileExtension" : null,
  "readableFilePresent" : false
}