{
  "objectInfo" : {
    "id" : "6ZA6YbXbH0le3suLKPJg2a",
    "name" : "Cleanse_upg_version",
    "type" : "CLEANSE",
    "metadata" : {
      "modelVersion" : {
        "major" : 1,
        "minor" : 0
      },
      "repoInfo" : {
        "repoHandle" : "6ZA6YbXbH0le3suLKPJg2a"
      },
      "contextAttributes" : [ ],
      "additionalInfo" : {
        "description" : null,
        "contentType" : "Binary",
        "documentState" : "VALID"
      }
    }
  },
  "dataFileExtension" : "json",
  "updateTime" : "2025-02-19T08:07:14.285Z",
  "objectRefs" : [ ],
  "readableFileExtension" : null,
  "readableFilePresent" : false
}